{"terrain_replacement_rules":[{"enabled":true,"equal":true,"primary":3,"replacement":6,"secondary":[30,31,0]},{"enabled":true,"equal":true,"primary":1,"replacement":6,"secondary":[30,31,0]},{"enabled":true,"equal":true,"primary":5,"replacement":6,"secondary":[30,31,0]},{"enabled":true,"equal":true,"primary":30,"replacement":6,"secondary":[1,3,0]},{"enabled":true,"equal":true,"primary":30,"replacement":6,"secondary":[1,3,0]},{"enabled":true,"equal":true,"primary":5,"replacement":3,"secondary":[1,0,0]},{"enabled":true,"equal":false,"primary":30,"replacement":6,"secondary":[30,31,0]},{"enabled":true,"equal":true,"primary":3,"replacement":4,"secondary":[5,0,0]},{"enabled":true,"equal":true,"primary":3,"replacement":2,"secondary":[1,0,0]},{"enabled":true,"equal":true,"primary":6,"replacement":4,"secondary":[3,0,0]},{"enabled":true,"equal":true,"primary":1,"replacement":2,"secondary":[6,0,0]}]}