{
    "mesh": {
        "vertices": [
            {
                "y": "-0.774596669241",
                "x": "0.61090513237",
                "z": "0.163691536871"
            },
            {
                "y": "-0.774596669241",
                "x": "0.163691536871",
                "z": "-0.61090513237"
            },
            {
                "y": "-9.9400667496E-13",
                "x": "-0.0599152608792",
                "z": "-0.998203466991"
            },
            {
                "y": "0.774596669242",
                "x": "0.163691536871",
                "z": "-0.61090513237"
            },
            {
                "y": "0.774596669242",
                "x": "0.61090513237",
                "z": "0.163691536871"
            },
            {
                "y": "-9.94205277692E-13",
                "x": "0.83451193012",
                "z": "0.550989871491"
            },
            {
                "y": "-0.774596669241",
                "x": "-0.61090513237",
                "z": "-0.163691536871"
            },
            {
                "y": "-0.774596669241",
                "x": "-0.163691536871",
                "z": "0.61090513237"
            },
            {
                "y": "-9.9400667496E-13",
                "x": "0.0599152608792",
                "z": "0.998203466991"
            },
            {
                "y": "0.774596669242",
                "x": "-0.163691536871",
                "z": "0.61090513237"
            },
            {
                "y": "0.774596669242",
                "x": "-0.61090513237",
                "z": "-0.163691536871"
            },
            {
                "y": "-9.9400667496E-13",
                "x": "-0.83451193012",
                "z": "-0.550989871491"
            }
        ],
        "polygons": [
            {
                "corners": [
                    "0",
                    "1",
                    "2",
                    "3",
                    "4",
                    "5"
                ]
            },
            {
                "corners": [
                    "6",
                    "7",
                    "8",
                    "9",
                    "10",
                    "11"
                ]
            },
            {
                "corners": [
                    "10",
                    "3",
                    "2",
                    "11"
                ]
            },
            {
                "corners": [
                    "11",
                    "2",
                    "1",
                    "6"
                ]
            },
            {
                "corners": [
                    "6",
                    "1",
                    "0",
                    "7"
                ]
            },
            {
                "corners": [
                    "7",
                    "0",
                    "5",
                    "8"
                ]
            },
            {
                "corners": [
                    "8",
                    "5",
                    "4",
                    "9"
                ]
            },
            {
                "corners": [
                    "9",
                    "4",
                    "3",
                    "10"
                ]
            }
        ]
    }
}
